Metadata-Version: 1.0
Name: prob-normal-binomial-dist-bee001
Version: 0.1
Summary: Gaussian distributions and Binomial Distributions
Home-page: UNKNOWN
Author: Chukwuezi Precious
Author-email: UNKNOWN
License: UNKNOWN
Platform: UNKNOWN
